forkme.py
forkme-0.11.dist-info/DESCRIPTION.rst
forkme-0.11.dist-info/METADATA
forkme-0.11.dist-info/RECORD
forkme-0.11.dist-info/WHEEL
forkme-0.11.dist-info/metadata.json
forkme-0.11.dist-info/top_level.txt
